colcon_ros_distro/__init__.py
colcon_ros_distro/package_augmentation/__init__.py
colcon_ros_distro/package_augmentation/ros_distro.py
colcon_ros_distro/package_discovery/__init__.py
colcon_ros_distro/package_discovery/ros_distro.py
colcon_ros_distro-0.1.0.dist-info/LICENSE
colcon_ros_distro-0.1.0.dist-info/METADATA
colcon_ros_distro-0.1.0.dist-info/WHEEL
colcon_ros_distro-0.1.0.dist-info/entry_points.txt
colcon_ros_distro-0.1.0.dist-info/top_level.txt
colcon_ros_distro-0.1.0.dist-info/zip-safe
colcon_ros_distro-0.1.0.dist-info/RECORD
